sparksql_upgrade/__init__.py
sparksql_upgrade/plugin.py
sparksql_upgrade/plugin_default_config.cfg
sparksql_upgrade/rules.py
sqlfluff_plugin_sparksql_upgrade-0.1.4.dist-info/METADATA
sqlfluff_plugin_sparksql_upgrade-0.1.4.dist-info/WHEEL
sqlfluff_plugin_sparksql_upgrade-0.1.4.dist-info/entry_points.txt
sqlfluff_plugin_sparksql_upgrade-0.1.4.dist-info/top_level.txt
sqlfluff_plugin_sparksql_upgrade-0.1.4.dist-info/RECORD
