Metadata-Version: 2.1
Name: sqlfluff-plugin-sparksql-upgrade
Version: 0.1.4
Summary: SQLFluff rules to help migrate your Spark SQL from 2.X to 3.X
Home-page: https://github.com/holdenk/spark-upgrade
Author: Holden Karau
Author-email: holden@pigscanfly.ca
License: ../LICENSE
Requires-Dist: sqlfluff ==2.3.2
